findreplace/__init__.py
findreplace/management/__init__.py
findreplace/management/commands/__init__.py
findreplace/management/commands/findreplace.py
django_findreplace-0.2.dist-info/LICENSE
django_findreplace-0.2.dist-info/METADATA
django_findreplace-0.2.dist-info/WHEEL
django_findreplace-0.2.dist-info/top_level.txt
django_findreplace-0.2.dist-info/RECORD
