Metadata-Version: 2.1
Name: django-findreplace
Version: 0.2
Summary: Django Find Replace
Maintainer-email: The Developer Society <studio@dev.ngo>
Project-URL: Homepage, https://github.com/developersociety/django-findreplace
Classifier: Intended Audience :: Developers
Classifier: License :: OSI Approved :: BSD License
Classifier: Operating System :: OS Independent
Classifier: Programming Language :: Python
Classifier: Programming Language :: Python :: 3
Classifier: Programming Language :: Python :: 3.9
Classifier: Programming Language :: Python :: 3.10
Classifier: Programming Language :: Python :: 3.11
Classifier: Programming Language :: Python :: 3.12
Classifier: Framework :: Django
Classifier: Framework :: Django :: 3.2
Classifier: Framework :: Django :: 4.2
Requires-Python: >=3.9
License-File: LICENSE
Requires-Dist: Django>=3.2
